libppo.so
planetplanet/__init__.py
planetplanet/constants.py
planetplanet/pool.py
planetplanet/version.py
planetplanet/detect/__init__.py
planetplanet/detect/jwst.py
planetplanet/detect/filter_files/080924ch1trans_full.txt
planetplanet/detect/filter_files/080924ch2trans_full.txt
planetplanet/detect/filter_files/080924ch3trans_full.txt
planetplanet/detect/filter_files/080924ch4trans_full.txt
planetplanet/detect/filter_files/miri_filter.csv
planetplanet/photo/__init__.py
planetplanet/photo/eyeball.c
planetplanet/photo/eyeball.py
planetplanet/photo/inclination.dat
planetplanet/photo/maps.py
planetplanet/photo/orbit.c
planetplanet/photo/posteriors.dat
planetplanet/photo/ppo.c
planetplanet/photo/ppo.h
planetplanet/photo/ppo.py
planetplanet/photo/structs.py
planetplanet/photo/theta.py
planetplanet/photo/trappist1.py
planetplanet-1.0.0.dist-info/DESCRIPTION.rst
planetplanet-1.0.0.dist-info/METADATA
planetplanet-1.0.0.dist-info/RECORD
planetplanet-1.0.0.dist-info/WHEEL
planetplanet-1.0.0.dist-info/metadata.json
planetplanet-1.0.0.dist-info/top_level.txt
